{"frames": {

"idle0.png":
{
	"frame": {"x":0,"y":0,"w":16,"h":32},
	"rotated": false,
	"trimmed": false,
	"spriteSourceSize": {"x":0,"y":0,"w":16,"h":32},
	"sourceSize": {"w":16,"h":32}
},
"idle45.png":
{
	"frame": {"x":16,"y":0,"w":15,"h":32},
	"rotated": false,
	"trimmed": false,
	"spriteSourceSize": {"x":0,"y":0,"w":15,"h":32},
	"sourceSize": {"w":15,"h":32}
},
"idle90.png":
{
	"frame": {"x":31,"y":0,"w":17,"h":32},
	"rotated": false,
	"trimmed": false,
	"spriteSourceSize": {"x":0,"y":0,"w":17,"h":32},
	"sourceSize": {"w":17,"h":32}
},
"idle270.png":
{
	"frame": {"x":48,"y":0,"w":17,"h":32},
	"rotated": false,
	"trimmed": false,
	"spriteSourceSize": {"x":0,"y":0,"w":17,"h":32},
	"sourceSize": {"w":17,"h":32}
},
"idle315.png":
{
	"frame": {"x":65,"y":0,"w":17,"h":32},
	"rotated": false,
	"trimmed": false,
	"spriteSourceSize": {"x":0,"y":0,"w":17,"h":32},
	"sourceSize": {"w":17,"h":32}
},
"run0_1.png":
{
	"frame": {"x":82,"y":0,"w":17,"h":32},
	"rotated": false,
	"trimmed": false,
	"spriteSourceSize": {"x":0,"y":0,"w":17,"h":32},
	"sourceSize": {"w":17,"h":32}
},
"run0_2.png":
{
	"frame": {"x":99,"y":0,"w":24,"h":31},
	"rotated": false,
	"trimmed": false,
	"spriteSourceSize": {"x":0,"y":0,"w":24,"h":31},
	"sourceSize": {"w":24,"h":31}
},
"run0_3.png":
{
	"frame": {"x":123,"y":0,"w":22,"h":32},
	"rotated": false,
	"trimmed": false,
	"spriteSourceSize": {"x":0,"y":0,"w":22,"h":32},
	"sourceSize": {"w":22,"h":32}
},
"run0_4.png":
{
	"frame": {"x":145,"y":0,"w":18,"h":32},
	"rotated": false,
	"trimmed": false,
	"spriteSourceSize": {"x":0,"y":0,"w":18,"h":32},
	"sourceSize": {"w":18,"h":32}
},
"run0_5.png":
{
	"frame": {"x":163,"y":0,"w":23,"h":31},
	"rotated": false,
	"trimmed": false,
	"spriteSourceSize": {"x":0,"y":0,"w":23,"h":31},
	"sourceSize": {"w":23,"h":31}
},
"run0_6.png":
{
	"frame": {"x":186,"y":0,"w":20,"h":32},
	"rotated": false,
	"trimmed": false,
	"spriteSourceSize": {"x":0,"y":0,"w":20,"h":32},
	"sourceSize": {"w":20,"h":32}
},
"run45_1.png":
{
	"frame": {"x":206,"y":0,"w":16,"h":32},
	"rotated": false,
	"trimmed": false,
	"spriteSourceSize": {"x":0,"y":0,"w":16,"h":32},
	"sourceSize": {"w":16,"h":32}
},
"run45_2.png":
{
	"frame": {"x":222,"y":0,"w":20,"h":31},
	"rotated": false,
	"trimmed": false,
	"spriteSourceSize": {"x":0,"y":0,"w":20,"h":31},
	"sourceSize": {"w":20,"h":31}
},
"run45_3.png":
{
	"frame": {"x":242,"y":0,"w":21,"h":32},
	"rotated": false,
	"trimmed": false,
	"spriteSourceSize": {"x":0,"y":0,"w":21,"h":32},
	"sourceSize": {"w":21,"h":32}
},
"run45_4.png":
{
	"frame": {"x":263,"y":0,"w":20,"h":32},
	"rotated": false,
	"trimmed": false,
	"spriteSourceSize": {"x":0,"y":0,"w":20,"h":32},
	"sourceSize": {"w":20,"h":32}
},
"run45_5.png":
{
	"frame": {"x":283,"y":0,"w":20,"h":31},
	"rotated": false,
	"trimmed": false,
	"spriteSourceSize": {"x":0,"y":0,"w":20,"h":31},
	"sourceSize": {"w":20,"h":31}
},
"run45_6.png":
{
	"frame": {"x":303,"y":0,"w":19,"h":32},
	"rotated": false,
	"trimmed": false,
	"spriteSourceSize": {"x":0,"y":0,"w":19,"h":32},
	"sourceSize": {"w":19,"h":32}
},
"run90_1.png":
{
	"frame": {"x":322,"y":0,"w":18,"h":32},
	"rotated": false,
	"trimmed": false,
	"spriteSourceSize": {"x":0,"y":0,"w":18,"h":32},
	"sourceSize": {"w":18,"h":32}
},
"run90_2.png":
{
	"frame": {"x":340,"y":0,"w":16,"h":31},
	"rotated": false,
	"trimmed": false,
	"spriteSourceSize": {"x":0,"y":0,"w":16,"h":31},
	"sourceSize": {"w":16,"h":31}
},
"run90_3.png":
{
	"frame": {"x":356,"y":0,"w":17,"h":32},
	"rotated": false,
	"trimmed": false,
	"spriteSourceSize": {"x":0,"y":0,"w":17,"h":32},
	"sourceSize": {"w":17,"h":32}
},
"run90_4.png":
{
	"frame": {"x":373,"y":0,"w":18,"h":32},
	"rotated": false,
	"trimmed": false,
	"spriteSourceSize": {"x":0,"y":0,"w":18,"h":32},
	"sourceSize": {"w":18,"h":32}
},
"run90_5.png":
{
	"frame": {"x":391,"y":0,"w":16,"h":31},
	"rotated": false,
	"trimmed": false,
	"spriteSourceSize": {"x":0,"y":0,"w":16,"h":31},
	"sourceSize": {"w":16,"h":31}
},
"run90_6.png":
{
	"frame": {"x":407,"y":0,"w":17,"h":32},
	"rotated": false,
	"trimmed": false,
	"spriteSourceSize": {"x":0,"y":0,"w":17,"h":32},
	"sourceSize": {"w":17,"h":32}
},
"run270_1.png":
{
	"frame": {"x":424,"y":0,"w":19,"h":32},
	"rotated": false,
	"trimmed": false,
	"spriteSourceSize": {"x":0,"y":0,"w":19,"h":32},
	"sourceSize": {"w":19,"h":32}
},
"run270_2.png":
{
	"frame": {"x":443,"y":0,"w":17,"h":31},
	"rotated": false,
	"trimmed": false,
	"spriteSourceSize": {"x":0,"y":0,"w":17,"h":31},
	"sourceSize": {"w":17,"h":31}
},
"run270_3.png":
{
	"frame": {"x":460,"y":0,"w":17,"h":32},
	"rotated": false,
	"trimmed": false,
	"spriteSourceSize": {"x":0,"y":0,"w":17,"h":32},
	"sourceSize": {"w":17,"h":32}
},
"run270_4.png":
{
	"frame": {"x":477,"y":0,"w":19,"h":32},
	"rotated": false,
	"trimmed": false,
	"spriteSourceSize": {"x":0,"y":0,"w":19,"h":32},
	"sourceSize": {"w":19,"h":32}
},
"run270_5.png":
{
	"frame": {"x":496,"y":0,"w":16,"h":31},
	"rotated": false,
	"trimmed": false,
	"spriteSourceSize": {"x":0,"y":0,"w":16,"h":31},
	"sourceSize": {"w":16,"h":31}
},
"run270_6.png":
{
	"frame": {"x":512,"y":0,"w":16,"h":32},
	"rotated": false,
	"trimmed": false,
	"spriteSourceSize": {"x":0,"y":0,"w":16,"h":32},
	"sourceSize": {"w":16,"h":32}
},
"run315_1.png":
{
	"frame": {"x":528,"y":0,"w":20,"h":32},
	"rotated": false,
	"trimmed": false,
	"spriteSourceSize": {"x":0,"y":0,"w":20,"h":32},
	"sourceSize": {"w":20,"h":32}
},
"run315_2.png":
{
	"frame": {"x":548,"y":0,"w":24,"h":31},
	"rotated": false,
	"trimmed": false,
	"spriteSourceSize": {"x":0,"y":0,"w":24,"h":31},
	"sourceSize": {"w":24,"h":31}
},
"run315_3.png":
{
	"frame": {"x":572,"y":0,"w":20,"h":32},
	"rotated": false,
	"trimmed": false,
	"spriteSourceSize": {"x":0,"y":0,"w":20,"h":32},
	"sourceSize": {"w":20,"h":32}
},
"run315_4.png":
{
	"frame": {"x":592,"y":0,"w":16,"h":32},
	"rotated": false,
	"trimmed": false,
	"spriteSourceSize": {"x":0,"y":0,"w":16,"h":32},
	"sourceSize": {"w":16,"h":32}
},
"run315_5.png":
{
	"frame": {"x":608,"y":0,"w":23,"h":31},
	"rotated": false,
	"trimmed": false,
	"spriteSourceSize": {"x":0,"y":0,"w":23,"h":31},
	"sourceSize": {"w":23,"h":31}
},
"run315_6.png":
{
	"frame": {"x":631,"y":0,"w":21,"h":32},
	"rotated": false,
	"trimmed": false,
	"spriteSourceSize": {"x":0,"y":0,"w":21,"h":32},
	"sourceSize": {"w":21,"h":32}
}},
"animations": {
	"idle": ["idle0.png","idle45.png","idle90.png","idle270.png","idle315.png"],
	"run0": ["run0_1.png","run0_2.png","run0_3.png","run0_4.png","run0_5.png","run0_6.png"],
	"run270": ["run270_1.png","run270_2.png","run270_3.png","run270_4.png","run270_5.png","run270_6.png"],
	"run315": ["run315_1.png","run315_2.png","run315_3.png","run315_4.png","run315_5.png","run315_6.png"],
	"run45": ["run45_1.png","run45_2.png","run45_3.png","run45_4.png","run45_5.png","run45_6.png"],
	"run90": ["run90_1.png","run90_2.png","run90_3.png","run90_4.png","run90_5.png","run90_6.png"]
},
"meta": {
	"app": "https://www.codeandweb.com/texturepacker",
	"version": "1.0",
	"image": "run.png",
	"format": "RGBA8888",
	"size": {"w":652,"h":32},
	"scale": "1",
	"smartupdate": "$TexturePacker:SmartUpdate:31ae07a750813705cdc1477e3a007f98:3a16b7ac419f296f37561bd2346c9942:0bfa41ad2432204f88f9f54b9f6b3241$"
}
}
